rootstalk/timestamp.py
rootstalk-0.0.3.dist-info/LICENSE
rootstalk-0.0.3.dist-info/METADATA
rootstalk-0.0.3.dist-info/WHEEL
rootstalk-0.0.3.dist-info/top_level.txt
rootstalk-0.0.3.dist-info/RECORD
