Metadata-Version: 2.1
Name: rootstalk
Version: 0.0.3
Summary: Frequently used Python utilties, now in one place.
Author-email: Chad Hovey <chovey@sandia.gov>
License: MIT License
Project-URL: Homepage, https://github.com/hovey/rootstalk
Project-URL: Bug Tracker, https://github.com/hovey/rootstalk/issues
Classifier: Programming Language :: Python :: 3
Classifier: License :: OSI Approved :: MIT License
Classifier: Operating System :: OS Independent
Requires-Python: >=3.7
License-File: LICENSE
Requires-Dist: black
Requires-Dist: flake8
Requires-Dist: pytest
Requires-Dist: pytest-cov
Requires-Dist: pyyaml
